source_metabase/__init__.py
source_metabase/manifest.yaml
source_metabase/run.py
source_metabase/source.py
airbyte_source_metabase-2.0.13.dist-info/METADATA
airbyte_source_metabase-2.0.13.dist-info/WHEEL
airbyte_source_metabase-2.0.13.dist-info/entry_points.txt
airbyte_source_metabase-2.0.13.dist-info/RECORD
