Metadata-Version: 2.1
Name: airbyte-source-metabase
Version: 2.0.13
Summary: Source implementation for Metabase.
Home-page: https://airbyte.com
License: MIT
Author: Airbyte
Author-email: contact@airbyte.io
Requires-Python: >=3.9,<3.12
Classifier: License :: OSI Approved :: MIT License
Classifier: Programming Language :: Python :: 3
Classifier: Programming Language :: Python :: 3.9
Classifier: Programming Language :: Python :: 3.10
Classifier: Programming Language :: Python :: 3.11
Requires-Dist: airbyte-cdk (>=0,<1)
Requires-Dist: requests (>=2.28.0,<3.0.0)
Requires-Dist: types-requests (>=2.27.30,<3.0.0)
Project-URL: Documentation, https://docs.airbyte.com/integrations/sources/metabase
Project-URL: Repository, https://github.com/airbytehq/airbyte
